smarthouse/__init__.py
smarthouse/action_decorators.py
smarthouse/app.py
smarthouse/device.py
smarthouse/device_generator.py
smarthouse/logger.py
smarthouse/storage.py
smarthouse/storage_keys.py
smarthouse/telegram_client.py
smarthouse/utils.py
smarthouse/yandex_cloud.py
smarthouse-2.3.0.dist-info/LICENSE.md
smarthouse-2.3.0.dist-info/METADATA
smarthouse-2.3.0.dist-info/WHEEL
smarthouse-2.3.0.dist-info/top_level.txt
smarthouse-2.3.0.dist-info/RECORD
