Metadata-Version: 2.1
Name: smarthouse
Version: 2.3.0
Summary: Smart House Scenarios
Home-page: https://smarthouselib.readthedocs.io/
Author: Ivan Kriuchkov
Author-email: vivenchik@gmail.com
License: MIT
Classifier: Intended Audience :: Developers
Classifier: License :: OSI Approved :: MIT License
Classifier: Programming Language :: Python
Classifier: Programming Language :: Python :: 3
Classifier: Programming Language :: Python :: 3.11
Classifier: Operating System :: OS Independent
License-File: LICENSE.md
Requires-Dist: aiohttp[speedups]
Requires-Dist: aiofiles
Requires-Dist: pyyaml
Requires-Dist: python-telegram-bot[all,ext]
Requires-Dist: telegram
Requires-Dist: pydantic
Requires-Dist: pydantic-settings
Requires-Dist: async-lru
Requires-Dist: astral
Provides-Extra: cloud
Requires-Dist: pyjwt ; extra == 'cloud'
Requires-Dist: cryptography ; extra == 'cloud'
Requires-Dist: aioboto3 ; extra == 'cloud'
Provides-Extra: dev
Requires-Dist: pip-tools ; extra == 'dev'
Requires-Dist: black ; extra == 'dev'
Requires-Dist: isort ; extra == 'dev'
Requires-Dist: mypy ; extra == 'dev'
Requires-Dist: types-PyYAML ; extra == 'dev'
Requires-Dist: types-aiofiles ; extra == 'dev'
Requires-Dist: flake8 ; extra == 'dev'
Requires-Dist: flake8-pyproject ; extra == 'dev'
Requires-Dist: pytest ; extra == 'dev'
Requires-Dist: pytest-mock ; extra == 'dev'
Requires-Dist: pytest-asyncio ; extra == 'dev'
Requires-Dist: pytest-aiohttp ; extra == 'dev'
Requires-Dist: pytest-xdist ; extra == 'dev'
Requires-Dist: pytest-cov ; extra == 'dev'
Requires-Dist: pytest-rerunfailures ; extra == 'dev'
Requires-Dist: no-implicit-optional ; extra == 'dev'
Requires-Dist: python-dotenv ; extra == 'dev'
Requires-Dist: twine ; extra == 'dev'
Provides-Extra: ha
Requires-Dist: homeassistant-api >=4 ; extra == 'ha'
